README.rst
setup.py
jinjatex/__init__.py
jinjatex.egg-info/PKG-INFO
jinjatex.egg-info/SOURCES.txt
jinjatex.egg-info/dependency_links.txt
jinjatex.egg-info/requires.txt
jinjatex.egg-info/top_level.txt