Metadata-Version: 1.1
Name: jinjatex
Version: 0.2
Summary: A wrapper to easily use Jinja2 for tex-templates.
Home-page: https://github.com/NotSpecial/jinjatex
Author: Alexander Dietmüller
Author-email: UNKNOWN
License: UNKNOWN
Download-URL: https://github.com/NotSpecial/jinjatex/releases/tag/0.2
Platform: UNKNOWN
